[{"msg":"down,511,401","time":0},{"msg":"move,512,398","time":5},{"msg":"move,512,393","time":9},{"msg":"move,511,388","time":16},{"msg":"move,509,381","time":16},{"msg":"move,506,378","time":17},{"msg":"move,503,380","time":17},{"msg":"move,498,390","time":16},{"msg":"move,494,404","time":17},{"msg":"move,492,413","time":17},{"msg":"move,495,415","time":16},{"msg":"move,501,411","time":17},{"msg":"move,507,404","time":17},{"msg":"move,514,392","time":17},{"msg":"move,519,380","time":16},{"msg":"move,521,372","time":17},{"msg":"move,521,369","time":16},{"msg":"move,521,370","time":33},{"msg":"move,522,372","time":17},{"msg":"move,526,381","time":17},{"msg":"move,529,392","time":17},{"msg":"move,528,409","time":17},{"msg":"move,517,429","time":17},{"msg":"move,500,447","time":16},{"msg":"move,484,458","time":16},{"msg":"move,472,462","time":17},{"msg":"move,469,460","time":17},{"msg":"move,470,459","time":17},{"msg":"up,465,454","time":0},{"msg":"down,538,433","time":204},{"msg":"move,534,437","time":12},{"msg":"move,533,439","time":17},{"msg":"move,536,438","time":16},{"msg":"move,543,433","time":17},{"msg":"move,552,426","time":17},{"msg":"move,563,415","time":16},{"msg":"move,569,406","time":17},{"msg":"move,568,402","time":17},{"msg":"move,560,405","time":17},{"msg":"move,548,417","time":16},{"msg":"move,538,432","time":16},{"msg":"move,534,442","time":17},{"msg":"move,537,442","time":17},{"msg":"move,544,442","time":17},{"msg":"move,553,443","time":16},{"msg":"move,563,444","time":17},{"msg":"move,571,442","time":17},{"msg":"move,573,440","time":17},{"msg":"up,568,435","time":0},{"msg":"down,597,432","time":170},{"msg":"move,598,427","time":13},{"msg":"move,599,416","time":16},{"msg":"move,602,396","time":17},{"msg":"move,602,372","time":17},{"msg":"move,602,355","time":16},{"msg":"move,601,349","time":17},{"msg":"move,599,348","time":16},{"msg":"up,594,343","time":1},{"msg":"down,574,387","time":120},{"msg":"move,577,385","time":13},{"msg":"move,594,381","time":17},{"msg":"move,615,378","time":16},{"msg":"move,630,377","time":17},{"msg":"move,640,377","time":17},{"msg":"move,641,378","time":16},{"msg":"up,636,373","time":1}]