[{"msg":"down,37,172","time":0},{"msg":"move,38,172","time":13},{"msg":"move,39,171","time":14},{"msg":"move,41,169","time":17},{"msg":"move,44,168","time":16},{"msg":"move,47,168","time":17},{"msg":"move,51,170","time":17},{"msg":"move,55,175","time":16},{"msg":"move,58,183","time":17},{"msg":"move,60,190","time":17},{"msg":"move,61,197","time":17},{"msg":"move,59,203","time":16},{"msg":"move,55,208","time":17},{"msg":"move,50,212","time":16},{"msg":"move,41,213","time":17},{"msg":"move,30,209","time":17},{"msg":"move,21,200","time":16},{"msg":"move,14,189","time":18},{"msg":"move,12,181","time":16},{"msg":"move,12,173","time":16},{"msg":"move,16,163","time":17},{"msg":"move,23,153","time":17},{"msg":"move,31,145","time":17},{"msg":"move,41,140","time":17},{"msg":"move,49,138","time":16},{"msg":"move,58,138","time":16},{"msg":"move,65,141","time":17},{"msg":"move,71,146","time":17},{"msg":"move,73,148","time":16},{"msg":"move,76,151","time":1},{"msg":"move,79,156","time":16},{"msg":"up,74,151","time":0},{"msg":"down,86,214","time":138},{"msg":"move,85,215","time":12},{"msg":"move,85,214","time":17},{"msg":"move,84,210","time":16},{"msg":"move,85,204","time":17},{"msg":"up,80,199","time":1},{"msg":"down,95,165","time":86},{"msg":"move,94,163","time":6},{"msg":"move,92,162","time":7},{"msg":"up,87,157","time":33},{"msg":"down,118,186","time":371},{"msg":"move,118,177","time":7},{"msg":"move,118,167","time":7},{"msg":"move,118,159","time":15},{"msg":"move,119,158","time":17},{"msg":"move,119,161","time":17},{"msg":"move,120,168","time":16},{"msg":"move,121,179","time":17},{"msg":"move,123,192","time":17},{"msg":"move,124,207","time":16},{"msg":"move,126,219","time":17},{"msg":"move,128,225","time":17},{"msg":"move,130,226","time":16},{"msg":"move,131,225","time":17},{"msg":"move,132,219","time":16},{"msg":"move,134,207","time":18},{"msg":"move,136,188","time":16},{"msg":"move,141,168","time":17},{"msg":"move,145,157","time":16},{"msg":"move,147,155","time":17},{"msg":"move,147,157","time":16},{"msg":"move,147,160","time":17},{"msg":"move,147,163","time":17},{"msg":"up,142,158","time":0},{"msg":"down,171,205","time":254},{"msg":"move,170,206","time":7},{"msg":"move,169,207","time":8},{"msg":"move,168,208","time":15},{"msg":"move,167,209","time":16},{"msg":"move,168,209","time":16},{"msg":"move,170,208","time":17},{"msg":"move,173,204","time":17},{"msg":"move,178,196","time":17},{"msg":"move,185,183","time":16},{"msg":"move,189,166","time":17},{"msg":"move,189,155","time":17},{"msg":"move,185,151","time":16},{"msg":"move,180,156","time":17},{"msg":"move,171,169","time":17},{"msg":"move,160,189","time":16},{"msg":"move,155,208","time":17},{"msg":"move,158,220","time":18},{"msg":"move,166,227","time":16},{"msg":"move,178,230","time":16},{"msg":"move,190,231","time":16},{"msg":"move,203,228","time":17},{"msg":"move,212,223","time":17},{"msg":"move,216,217","time":17},{"msg":"move,217,214","time":16},{"msg":"up,212,209","time":0}]